ab_engine/__init__.py
ab_engine/class_tools.py
ab_engine/error.py
ab_engine/db/__init__.py
ab_engine/db/driver.py
ab_engine/db/driver_mysql.py
ab_engine/db/driver_postgresql.py
ab_engine/db/driver_sqlite.py
ab_engine/db/option.py
ab_engine/db/processor.py
ab_engine/db/table.py
ab_engine/env/__init__.py
ab_engine/env/config.py
ab_engine/env/db_context.py
ab_engine/env/timer.py
ab_engine/rpc/__init__.py
ab_engine/rpc/fnc.py
ab_engine/rpc/json_rpc.py
ab_engine/rpc/rpc.py
ab_engine-0.1.2.dist-info/METADATA
ab_engine-0.1.2.dist-info/WHEEL
ab_engine-0.1.2.dist-info/top_level.txt
ab_engine-0.1.2.dist-info/RECORD
