Metadata-Version: 2.4
Name: ab_engine
Version: 0.1.2
Summary: Library of standard modules
Author-email: Andrew Bulatov <BulatovAndrew@gmail.com>
License-Expression: MIT
Project-URL: Repository, https://github.com/a-bulatov/ab_engine
Requires-Python: >=3.10
Requires-Dist: json5>=0.12.0
Requires-Dist: psycopg>=3.2.9
Requires-Dist: pyaml>=25.7.0
Requires-Dist: toml>=0.10.2
